quant/__init__.py
quant/application/__init__.py
quant/application/app.py
quant/application/app_factory.py
quant/application/service/__init__.py
quant/application/service/ticker_data_service.py
quant/application/service/ticker_data_sync_service.py
quant/common/__init__.py
quant/common/consts/__init__.py
quant/common/consts/securities.py
quant/common/consts/time.py
quant/common/utils/__init__.py
quant/common/utils/log.py
quant/common/utils/time_util.py
quant/domain/__init__.py
quant/domain/ticker/__init__.py
quant/domain/ticker/entity/__init__.py
quant/domain/ticker/entity/ticker.py
quant/domain/ticker/entity/ticker_action.py
quant/domain/ticker/entity/ticker_history.py
quant/domain/ticker/repository/__init__.py
quant/domain/ticker/repository/ticker_action_repository.py
quant/domain/ticker/repository/ticker_history_repository.py
quant/domain/ticker/repository/ticker_repository.py
quant/domain/yfinance_ticker/__init__.py
quant/domain/yfinance_ticker/entity/__init__.py
quant/domain/yfinance_ticker/entity/ticker.py
quant/domain/yfinance_ticker/entity/ticker_action.py
quant/domain/yfinance_ticker/entity/ticker_history.py
quant/domain/yfinance_ticker/repository/__init__.py
quant/domain/yfinance_ticker/repository/yfinance_repository.py
quant/infrastructure/__init__.py
quant/infrastructure/database/__init__.py
quant/infrastructure/database/engine.py
quant/infrastructure/database/orm/__init__.py
quant/infrastructure/database/orm/ticker_action_po.py
quant/infrastructure/database/orm/ticker_history_po.py
quant/infrastructure/database/orm/ticker_po.py
quant/infrastructure/database/ticker.py
quant/infrastructure/database/ticker_action.py
quant/infrastructure/database/ticker_history.py
quant/infrastructure/external_service/__init__.py
quant/infrastructure/external_service/yfinance/__init__.py
quant/infrastructure/external_service/yfinance/yfinance.py
quant/infrastructure/repository/__init__.py
quant/infrastructure/repository/ticker_action_repository.py
eddie_quant-0.0.11.dist-info/METADATA
eddie_quant-0.0.11.dist-info/WHEEL
eddie_quant-0.0.11.dist-info/RECORD
